btrup.py
btrup-1.0.2.dist-info/licenses/LICENSE
btrup-1.0.2.dist-info/METADATA
btrup-1.0.2.dist-info/WHEEL
btrup-1.0.2.dist-info/entry_points.txt
btrup-1.0.2.dist-info/top_level.txt
btrup-1.0.2.dist-info/RECORD
