Metadata-Version: 2.4
Name: btrup
Version: 1.0.2
Summary: BtrUp: Btrfs + Borg backup script
Author-email: Toon Verstraelen <toon.verstraelen@ugent.be>
License-Expression: GPL-3.0-or-later
Project-URL: Documentation, https://github.com/reproducible-reporting/btrup/
Project-URL: Issues, https://github.com/reproducible-reporting/btrup/issues
Project-URL: Source, https://github.com/reproducible-reporting/btrupt/
Project-URL: Changelog, https://github.com/reproducible-reporting/btrup/blob/main/CHANGELOG.md
Classifier: Development Status :: 4 - Beta
Classifier: Environment :: Console
Classifier: Operating System :: POSIX
Classifier: Programming Language :: Python :: 3
Classifier: Programming Language :: Python :: 3.11
Classifier: Programming Language :: Python :: 3.12
Classifier: Programming Language :: Python :: 3.13
Classifier: Topic :: System :: Archiving :: Backup
Requires-Python: >=3.11
License-File: LICENSE
Requires-Dist: attrs>=24.2.0
Requires-Dist: cattrs>=24.1.1
Provides-Extra: dev
Requires-Dist: pytest; extra == "dev"
Dynamic: license-file
